google_utils/__init__.py
google_utils/core.py
google_utils/error.py
google_utils/result.py
google_utils-1.0.3.dist-info/LICENSE
google_utils-1.0.3.dist-info/METADATA
google_utils-1.0.3.dist-info/WHEEL
google_utils-1.0.3.dist-info/top_level.txt
google_utils-1.0.3.dist-info/RECORD
