Metadata-Version: 2.1
Name: google-utils
Version: 1.0.3
Summary: A utility package to interact with google.com
Home-page: https://github.com/medjedqt/google-utils
Author: medjed
Author-email: imoshugi01@gmail.com
License: UNKNOWN
Platform: UNKNOWN
Classifier: Programming Language :: Python :: 3
Classifier: License :: OSI Approved :: GNU General Public License v3 (GPLv3)
Classifier: Operating System :: OS Independent
Classifier: Development Status :: 5 - Production/Stable
Classifier: Topic :: Utilities
Requires-Python: >=3.6
Requires-Dist: bs4
Requires-Dist: requests
